CHANGELOG.md
MANIFEST.in
README.md
setup.cfg
setup.py
azure/__init__.py
azure/digitaltwins/__init__.py
azure/digitaltwins/core/__init__.py
azure/digitaltwins/core/_digitaltwins_client.py
azure/digitaltwins/core/_utils.py
azure/digitaltwins/core/_version.py
azure/digitaltwins/core/_generated/__init__.py
azure/digitaltwins/core/_generated/_azure_digital_twins_api.py
azure/digitaltwins/core/_generated/_configuration.py
azure/digitaltwins/core/_generated/aio/__init__.py
azure/digitaltwins/core/_generated/aio/_azure_digital_twins_api.py
azure/digitaltwins/core/_generated/aio/_configuration.py
azure/digitaltwins/core/_generated/aio/operations/__init__.py
azure/digitaltwins/core/_generated/aio/operations/_digital_twin_models_operations.py
azure/digitaltwins/core/_generated/aio/operations/_digital_twins_operations.py
azure/digitaltwins/core/_generated/aio/operations/_event_routes_operations.py
azure/digitaltwins/core/_generated/aio/operations/_query_operations.py
azure/digitaltwins/core/_generated/models/__init__.py
azure/digitaltwins/core/_generated/models/_models.py
azure/digitaltwins/core/_generated/models/_models_py3.py
azure/digitaltwins/core/_generated/operations/__init__.py
azure/digitaltwins/core/_generated/operations/_digital_twin_models_operations.py
azure/digitaltwins/core/_generated/operations/_digital_twins_operations.py
azure/digitaltwins/core/_generated/operations/_event_routes_operations.py
azure/digitaltwins/core/_generated/operations/_query_operations.py
azure/digitaltwins/core/aio/__init__.py
azure/digitaltwins/core/aio/_digitaltwins_client_async.py
azure_digitaltwins_core_patched.egg-info/PKG-INFO
azure_digitaltwins_core_patched.egg-info/SOURCES.txt
azure_digitaltwins_core_patched.egg-info/dependency_links.txt
azure_digitaltwins_core_patched.egg-info/not-zip-safe
azure_digitaltwins_core_patched.egg-info/requires.txt
azure_digitaltwins_core_patched.egg-info/top_level.txt
samples/Readme.md
samples/dt_component_lifecycle.py
samples/dt_create_digitaltwins_service_client.py
samples/dt_digitaltwins_get.py
samples/dt_digitaltwins_lifecycle.py
samples/dt_digitaltwins_query.py
samples/dt_event_routes_get.py
samples/dt_event_routes_list.py
samples/dt_incoming_relationships_list.py
samples/dt_models_get.py
samples/dt_models_lifecycle.py
samples/dt_models_list.py
